mpnm/_Base.py
mpnm/__init__.py
mpnm/_algorithm.py
mpnm/_network.py
mpnm/_phase.py
mpnm/_topotools.py
mpnm/tools_numba.py
mpnm-2024.8.31.16.31.dist-info/LICENSE
mpnm-2024.8.31.16.31.dist-info/METADATA
mpnm-2024.8.31.16.31.dist-info/WHEEL
mpnm-2024.8.31.16.31.dist-info/top_level.txt
mpnm-2024.8.31.16.31.dist-info/RECORD
