Metadata-Version: 2.1
Name: mpnm
Version: 2024.8.31.16.31
Summary: My short description for my project.
Home-page: https://github.com/yojeep/multi-physic-network-model
Author: yojeep
Author-email: 1379690602@qq.com
License: MIT
Classifier: License :: OSI Approved :: MIT License
Classifier: Programming Language :: Python
Classifier: Programming Language :: Python :: 3
Classifier: Programming Language :: Python :: 3.6
Classifier: Programming Language :: Python :: Implementation :: CPython
Classifier: Programming Language :: Python :: Implementation :: PyPy
Requires-Python: >=3.6.0
License-File: LICENSE
Requires-Dist: numpy
Requires-Dist: numba
Requires-Dist: pypardiso
Requires-Dist: scipy
Requires-Dist: meshio
Requires-Dist: vtk
Requires-Dist: pandas
Requires-Dist: scikit-learn
